kcc_joel/__init__.py
kcc_joel/KrakenCoinComparator.py
kcc_joel/utils.py
kcc_joel-0.1.0.dist-info/METADATA
kcc_joel-0.1.0.dist-info/WHEEL
kcc_joel-0.1.0.dist-info/RECORD
